[
        {
            "entity": {
                "name": "/vulnerabilities/sqli*"
            },
            "entityChanges": {
                "type": "wildcard",
                "signatureOverrides": [
                    {
                        "signatureId": 200002147,
                        "enabled": false
                    },
                    {
                        "signatureId": 200002835,
                        "enabled": false
                    },
                    {
                        "signatureId": 200002476,
                        "enabled": false
                    },
                    {
                        "signatureId": 200015125,
                        "enabled": false
                    }
                ]
            },
            "entityType": "url",
            "action": "add-or-update"
        }
    ]
